[
  {
    "id": 500000,
    "desc": "角色-1-等级1",
    "role_id": 400000,
    "level": 1,
    "need_exp": 100
  },
  {
    "id": 500001,
    "desc": "角色-1-等级2",
    "role_id": 400000,
    "level": 2,
    "need_exp": 100
  },
  {
    "id": 500002,
    "desc": "角色-1-等级3",
    "role_id": 400000,
    "level": 3,
    "need_exp": 100
  },
  {
    "id": 500003,
    "desc": "角色-1-等级4",
    "role_id": 400000,
    "level": 4,
    "need_exp": 100
  },
  {
    "id": 500004,
    "desc": "角色-1-等级5",
    "role_id": 400000,
    "level": 5,
    "need_exp": 100
  },
  {
    "id": 500005,
    "desc": "角色-1-等级6",
    "role_id": 400000,
    "level": 6,
    "need_exp": 100
  },
  {
    "id": 500006,
    "desc": "角色-1-等级7",
    "role_id": 400000,
    "level": 7,
    "need_exp": 100
  },
  {
    "id": 500007,
    "desc": "角色-1-等级8",
    "role_id": 400000,
    "level": 8,
    "need_exp": 100
  },
  {
    "id": 500008,
    "desc": "角色-1-等级9",
    "role_id": 400000,
    "level": 9,
    "need_exp": 100
  },
  {
    "id": 500009,
    "desc": "角色-1-等级10",
    "role_id": 400000,
    "level": 10,
    "need_exp": 100
  },
  {
    "id": 500010,
    "desc": "角色-1-等级11",
    "role_id": 400000,
    "level": 11,
    "need_exp": 100
  },
  {
    "id": 500011,
    "desc": "角色-1-等级12",
    "role_id": 400000,
    "level": 12,
    "need_exp": 100
  },
  {
    "id": 500012,
    "desc": "角色-1-等级13",
    "role_id": 400000,
    "level": 13,
    "need_exp": 100
  },
  {
    "id": 500013,
    "desc": "角色-1-等级14",
    "role_id": 400000,
    "level": 14,
    "need_exp": 100
  },
  {
    "id": 500014,
    "desc": "角色-1-等级15",
    "role_id": 400000,
    "level": 15,
    "need_exp": 100
  },
  {
    "id": 500015,
    "desc": "角色-1-等级16",
    "role_id": 400000,
    "level": 16,
    "need_exp": 100
  },
  {
    "id": 500016,
    "desc": "角色-1-等级17",
    "role_id": 400000,
    "level": 17,
    "need_exp": 100
  },
  {
    "id": 500017,
    "desc": "角色-1-等级18",
    "role_id": 400000,
    "level": 18,
    "need_exp": 100
  },
  {
    "id": 500018,
    "desc": "角色-1-等级19",
    "role_id": 400000,
    "level": 19,
    "need_exp": 100
  },
  {
    "id": 500019,
    "desc": "角色-1-等级20",
    "role_id": 400000,
    "level": 20,
    "need_exp": 100
  },
  {
    "id": 500020,
    "desc": "角色-1-等级21",
    "role_id": 400000,
    "level": 21,
    "need_exp": 100
  },
  {
    "id": 500021,
    "desc": "角色-1-等级22",
    "role_id": 400000,
    "level": 22,
    "need_exp": 100
  },
  {
    "id": 500022,
    "desc": "角色-1-等级23",
    "role_id": 400000,
    "level": 23,
    "need_exp": 100
  },
  {
    "id": 500023,
    "desc": "角色-1-等级24",
    "role_id": 400000,
    "level": 24,
    "need_exp": 100
  },
  {
    "id": 500024,
    "desc": "角色-1-等级25",
    "role_id": 400000,
    "level": 25,
    "need_exp": 100
  },
  {
    "id": 500025,
    "desc": "角色-1-等级26",
    "role_id": 400000,
    "level": 26,
    "need_exp": 100
  },
  {
    "id": 500026,
    "desc": "角色-1-等级27",
    "role_id": 400000,
    "level": 27,
    "need_exp": 100
  },
  {
    "id": 500027,
    "desc": "角色-1-等级28",
    "role_id": 400000,
    "level": 28,
    "need_exp": 100
  },
  {
    "id": 500028,
    "desc": "角色-1-等级29",
    "role_id": 400000,
    "level": 29,
    "need_exp": 100
  },
  {
    "id": 500029,
    "desc": "角色-1-等级30",
    "role_id": 400000,
    "level": 30,
    "need_exp": 100
  },
  {
    "id": 500030,
    "desc": "角色-1-等级31",
    "role_id": 400000,
    "level": 31,
    "need_exp": 100
  },
  {
    "id": 500031,
    "desc": "角色-1-等级32",
    "role_id": 400000,
    "level": 32,
    "need_exp": 100
  },
  {
    "id": 500032,
    "desc": "角色-1-等级33",
    "role_id": 400000,
    "level": 33,
    "need_exp": 100
  },
  {
    "id": 500033,
    "desc": "角色-1-等级34",
    "role_id": 400000,
    "level": 34,
    "need_exp": 100
  },
  {
    "id": 500034,
    "desc": "角色-1-等级35",
    "role_id": 400000,
    "level": 35,
    "need_exp": 100
  },
  {
    "id": 500035,
    "desc": "角色-1-等级36",
    "role_id": 400000,
    "level": 36,
    "need_exp": 100
  },
  {
    "id": 500036,
    "desc": "角色-1-等级37",
    "role_id": 400000,
    "level": 37,
    "need_exp": 100
  },
  {
    "id": 500037,
    "desc": "角色-1-等级38",
    "role_id": 400000,
    "level": 38,
    "need_exp": 100
  },
  {
    "id": 500038,
    "desc": "角色-1-等级39",
    "role_id": 400000,
    "level": 39,
    "need_exp": 100
  },
  {
    "id": 500039,
    "desc": "角色-1-等级40",
    "role_id": 400000,
    "level": 40,
    "need_exp": 100
  },
  {
    "id": 500040,
    "desc": "角色-1-等级41",
    "role_id": 400000,
    "level": 41,
    "need_exp": 100
  },
  {
    "id": 500041,
    "desc": "角色-1-等级42",
    "role_id": 400000,
    "level": 42,
    "need_exp": 100
  },
  {
    "id": 500042,
    "desc": "角色-1-等级43",
    "role_id": 400000,
    "level": 43,
    "need_exp": 100
  },
  {
    "id": 500043,
    "desc": "角色-1-等级44",
    "role_id": 400000,
    "level": 44,
    "need_exp": 100
  },
  {
    "id": 500044,
    "desc": "角色-1-等级45",
    "role_id": 400000,
    "level": 45,
    "need_exp": 100
  },
  {
    "id": 500045,
    "desc": "角色-1-等级46",
    "role_id": 400000,
    "level": 46,
    "need_exp": 100
  },
  {
    "id": 500046,
    "desc": "角色-1-等级47",
    "role_id": 400000,
    "level": 47,
    "need_exp": 100
  },
  {
    "id": 500047,
    "desc": "角色-1-等级48",
    "role_id": 400000,
    "level": 48,
    "need_exp": 100
  },
  {
    "id": 500048,
    "desc": "角色-1-等级49",
    "role_id": 400000,
    "level": 49,
    "need_exp": 100
  },
  {
    "id": 500049,
    "desc": "角色-1-等级50",
    "role_id": 400000,
    "level": 50,
    "need_exp": 100
  },
  {
    "id": 500050,
    "desc": "角色-2-等级1",
    "role_id": 400001,
    "level": 1,
    "need_exp": 100
  },
  {
    "id": 500051,
    "desc": "角色-2-等级2",
    "role_id": 400001,
    "level": 2,
    "need_exp": 100
  },
  {
    "id": 500052,
    "desc": "角色-2-等级3",
    "role_id": 400001,
    "level": 3,
    "need_exp": 100
  },
  {
    "id": 500053,
    "desc": "角色-2-等级4",
    "role_id": 400001,
    "level": 4,
    "need_exp": 100
  },
  {
    "id": 500054,
    "desc": "角色-2-等级5",
    "role_id": 400001,
    "level": 5,
    "need_exp": 100
  },
  {
    "id": 500055,
    "desc": "角色-2-等级6",
    "role_id": 400001,
    "level": 6,
    "need_exp": 100
  },
  {
    "id": 500056,
    "desc": "角色-2-等级7",
    "role_id": 400001,
    "level": 7,
    "need_exp": 100
  },
  {
    "id": 500057,
    "desc": "角色-2-等级8",
    "role_id": 400001,
    "level": 8,
    "need_exp": 100
  },
  {
    "id": 500058,
    "desc": "角色-2-等级9",
    "role_id": 400001,
    "level": 9,
    "need_exp": 100
  },
  {
    "id": 500059,
    "desc": "角色-2-等级10",
    "role_id": 400001,
    "level": 10,
    "need_exp": 100
  },
  {
    "id": 500060,
    "desc": "角色-2-等级11",
    "role_id": 400001,
    "level": 11,
    "need_exp": 100
  },
  {
    "id": 500061,
    "desc": "角色-2-等级12",
    "role_id": 400001,
    "level": 12,
    "need_exp": 100
  },
  {
    "id": 500062,
    "desc": "角色-2-等级13",
    "role_id": 400001,
    "level": 13,
    "need_exp": 100
  },
  {
    "id": 500063,
    "desc": "角色-2-等级14",
    "role_id": 400001,
    "level": 14,
    "need_exp": 100
  },
  {
    "id": 500064,
    "desc": "角色-2-等级15",
    "role_id": 400001,
    "level": 15,
    "need_exp": 100
  },
  {
    "id": 500065,
    "desc": "角色-2-等级16",
    "role_id": 400001,
    "level": 16,
    "need_exp": 100
  },
  {
    "id": 500066,
    "desc": "角色-2-等级17",
    "role_id": 400001,
    "level": 17,
    "need_exp": 100
  },
  {
    "id": 500067,
    "desc": "角色-2-等级18",
    "role_id": 400001,
    "level": 18,
    "need_exp": 100
  },
  {
    "id": 500068,
    "desc": "角色-2-等级19",
    "role_id": 400001,
    "level": 19,
    "need_exp": 100
  },
  {
    "id": 500069,
    "desc": "角色-2-等级20",
    "role_id": 400001,
    "level": 20,
    "need_exp": 100
  },
  {
    "id": 500070,
    "desc": "角色-2-等级21",
    "role_id": 400001,
    "level": 21,
    "need_exp": 100
  },
  {
    "id": 500071,
    "desc": "角色-2-等级22",
    "role_id": 400001,
    "level": 22,
    "need_exp": 100
  },
  {
    "id": 500072,
    "desc": "角色-2-等级23",
    "role_id": 400001,
    "level": 23,
    "need_exp": 100
  },
  {
    "id": 500073,
    "desc": "角色-2-等级24",
    "role_id": 400001,
    "level": 24,
    "need_exp": 100
  },
  {
    "id": 500074,
    "desc": "角色-2-等级25",
    "role_id": 400001,
    "level": 25,
    "need_exp": 100
  },
  {
    "id": 500075,
    "desc": "角色-2-等级26",
    "role_id": 400001,
    "level": 26,
    "need_exp": 100
  },
  {
    "id": 500076,
    "desc": "角色-2-等级27",
    "role_id": 400001,
    "level": 27,
    "need_exp": 100
  },
  {
    "id": 500077,
    "desc": "角色-2-等级28",
    "role_id": 400001,
    "level": 28,
    "need_exp": 100
  },
  {
    "id": 500078,
    "desc": "角色-2-等级29",
    "role_id": 400001,
    "level": 29,
    "need_exp": 100
  },
  {
    "id": 500079,
    "desc": "角色-2-等级30",
    "role_id": 400001,
    "level": 30,
    "need_exp": 100
  },
  {
    "id": 500080,
    "desc": "角色-2-等级31",
    "role_id": 400001,
    "level": 31,
    "need_exp": 100
  },
  {
    "id": 500081,
    "desc": "角色-2-等级32",
    "role_id": 400001,
    "level": 32,
    "need_exp": 100
  },
  {
    "id": 500082,
    "desc": "角色-2-等级33",
    "role_id": 400001,
    "level": 33,
    "need_exp": 100
  },
  {
    "id": 500083,
    "desc": "角色-2-等级34",
    "role_id": 400001,
    "level": 34,
    "need_exp": 100
  },
  {
    "id": 500084,
    "desc": "角色-2-等级35",
    "role_id": 400001,
    "level": 35,
    "need_exp": 100
  },
  {
    "id": 500085,
    "desc": "角色-2-等级36",
    "role_id": 400001,
    "level": 36,
    "need_exp": 100
  },
  {
    "id": 500086,
    "desc": "角色-2-等级37",
    "role_id": 400001,
    "level": 37,
    "need_exp": 100
  },
  {
    "id": 500087,
    "desc": "角色-2-等级38",
    "role_id": 400001,
    "level": 38,
    "need_exp": 100
  },
  {
    "id": 500088,
    "desc": "角色-2-等级39",
    "role_id": 400001,
    "level": 39,
    "need_exp": 100
  },
  {
    "id": 500089,
    "desc": "角色-2-等级40",
    "role_id": 400001,
    "level": 40,
    "need_exp": 100
  },
  {
    "id": 500090,
    "desc": "角色-2-等级41",
    "role_id": 400001,
    "level": 41,
    "need_exp": 100
  },
  {
    "id": 500091,
    "desc": "角色-2-等级42",
    "role_id": 400001,
    "level": 42,
    "need_exp": 100
  },
  {
    "id": 500092,
    "desc": "角色-2-等级43",
    "role_id": 400001,
    "level": 43,
    "need_exp": 100
  },
  {
    "id": 500093,
    "desc": "角色-2-等级44",
    "role_id": 400001,
    "level": 44,
    "need_exp": 100
  },
  {
    "id": 500094,
    "desc": "角色-2-等级45",
    "role_id": 400001,
    "level": 45,
    "need_exp": 100
  },
  {
    "id": 500095,
    "desc": "角色-2-等级46",
    "role_id": 400001,
    "level": 46,
    "need_exp": 100
  },
  {
    "id": 500096,
    "desc": "角色-2-等级47",
    "role_id": 400001,
    "level": 47,
    "need_exp": 100
  },
  {
    "id": 500097,
    "desc": "角色-2-等级48",
    "role_id": 400001,
    "level": 48,
    "need_exp": 100
  },
  {
    "id": 500098,
    "desc": "角色-2-等级49",
    "role_id": 400001,
    "level": 49,
    "need_exp": 100
  },
  {
    "id": 500099,
    "desc": "角色-2-等级50",
    "role_id": 400001,
    "level": 50,
    "need_exp": 100
  },
  {
    "id": 500100,
    "desc": "角色-3-等级1",
    "role_id": 400002,
    "level": 1,
    "need_exp": 100
  },
  {
    "id": 500101,
    "desc": "角色-3-等级2",
    "role_id": 400002,
    "level": 2,
    "need_exp": 100
  },
  {
    "id": 500102,
    "desc": "角色-3-等级3",
    "role_id": 400002,
    "level": 3,
    "need_exp": 100
  },
  {
    "id": 500103,
    "desc": "角色-3-等级4",
    "role_id": 400002,
    "level": 4,
    "need_exp": 100
  },
  {
    "id": 500104,
    "desc": "角色-3-等级5",
    "role_id": 400002,
    "level": 5,
    "need_exp": 100
  },
  {
    "id": 500105,
    "desc": "角色-3-等级6",
    "role_id": 400002,
    "level": 6,
    "need_exp": 100
  },
  {
    "id": 500106,
    "desc": "角色-3-等级7",
    "role_id": 400002,
    "level": 7,
    "need_exp": 100
  },
  {
    "id": 500107,
    "desc": "角色-3-等级8",
    "role_id": 400002,
    "level": 8,
    "need_exp": 100
  },
  {
    "id": 500108,
    "desc": "角色-3-等级9",
    "role_id": 400002,
    "level": 9,
    "need_exp": 100
  },
  {
    "id": 500109,
    "desc": "角色-3-等级10",
    "role_id": 400002,
    "level": 10,
    "need_exp": 100
  },
  {
    "id": 500110,
    "desc": "角色-3-等级11",
    "role_id": 400002,
    "level": 11,
    "need_exp": 100
  },
  {
    "id": 500111,
    "desc": "角色-3-等级12",
    "role_id": 400002,
    "level": 12,
    "need_exp": 100
  },
  {
    "id": 500112,
    "desc": "角色-3-等级13",
    "role_id": 400002,
    "level": 13,
    "need_exp": 100
  },
  {
    "id": 500113,
    "desc": "角色-3-等级14",
    "role_id": 400002,
    "level": 14,
    "need_exp": 100
  },
  {
    "id": 500114,
    "desc": "角色-3-等级15",
    "role_id": 400002,
    "level": 15,
    "need_exp": 100
  },
  {
    "id": 500115,
    "desc": "角色-3-等级16",
    "role_id": 400002,
    "level": 16,
    "need_exp": 100
  },
  {
    "id": 500116,
    "desc": "角色-3-等级17",
    "role_id": 400002,
    "level": 17,
    "need_exp": 100
  },
  {
    "id": 500117,
    "desc": "角色-3-等级18",
    "role_id": 400002,
    "level": 18,
    "need_exp": 100
  },
  {
    "id": 500118,
    "desc": "角色-3-等级19",
    "role_id": 400002,
    "level": 19,
    "need_exp": 100
  },
  {
    "id": 500119,
    "desc": "角色-3-等级20",
    "role_id": 400002,
    "level": 20,
    "need_exp": 100
  },
  {
    "id": 500120,
    "desc": "角色-3-等级21",
    "role_id": 400002,
    "level": 21,
    "need_exp": 100
  },
  {
    "id": 500121,
    "desc": "角色-3-等级22",
    "role_id": 400002,
    "level": 22,
    "need_exp": 100
  },
  {
    "id": 500122,
    "desc": "角色-3-等级23",
    "role_id": 400002,
    "level": 23,
    "need_exp": 100
  },
  {
    "id": 500123,
    "desc": "角色-3-等级24",
    "role_id": 400002,
    "level": 24,
    "need_exp": 100
  },
  {
    "id": 500124,
    "desc": "角色-3-等级25",
    "role_id": 400002,
    "level": 25,
    "need_exp": 100
  },
  {
    "id": 500125,
    "desc": "角色-3-等级26",
    "role_id": 400002,
    "level": 26,
    "need_exp": 100
  },
  {
    "id": 500126,
    "desc": "角色-3-等级27",
    "role_id": 400002,
    "level": 27,
    "need_exp": 100
  },
  {
    "id": 500127,
    "desc": "角色-3-等级28",
    "role_id": 400002,
    "level": 28,
    "need_exp": 100
  },
  {
    "id": 500128,
    "desc": "角色-3-等级29",
    "role_id": 400002,
    "level": 29,
    "need_exp": 100
  },
  {
    "id": 500129,
    "desc": "角色-3-等级30",
    "role_id": 400002,
    "level": 30,
    "need_exp": 100
  },
  {
    "id": 500130,
    "desc": "角色-3-等级31",
    "role_id": 400002,
    "level": 31,
    "need_exp": 100
  },
  {
    "id": 500131,
    "desc": "角色-3-等级32",
    "role_id": 400002,
    "level": 32,
    "need_exp": 100
  },
  {
    "id": 500132,
    "desc": "角色-3-等级33",
    "role_id": 400002,
    "level": 33,
    "need_exp": 100
  },
  {
    "id": 500133,
    "desc": "角色-3-等级34",
    "role_id": 400002,
    "level": 34,
    "need_exp": 100
  },
  {
    "id": 500134,
    "desc": "角色-3-等级35",
    "role_id": 400002,
    "level": 35,
    "need_exp": 100
  },
  {
    "id": 500135,
    "desc": "角色-3-等级36",
    "role_id": 400002,
    "level": 36,
    "need_exp": 100
  },
  {
    "id": 500136,
    "desc": "角色-3-等级37",
    "role_id": 400002,
    "level": 37,
    "need_exp": 100
  },
  {
    "id": 500137,
    "desc": "角色-3-等级38",
    "role_id": 400002,
    "level": 38,
    "need_exp": 100
  },
  {
    "id": 500138,
    "desc": "角色-3-等级39",
    "role_id": 400002,
    "level": 39,
    "need_exp": 100
  },
  {
    "id": 500139,
    "desc": "角色-3-等级40",
    "role_id": 400002,
    "level": 40,
    "need_exp": 100
  },
  {
    "id": 500140,
    "desc": "角色-3-等级41",
    "role_id": 400002,
    "level": 41,
    "need_exp": 100
  },
  {
    "id": 500141,
    "desc": "角色-3-等级42",
    "role_id": 400002,
    "level": 42,
    "need_exp": 100
  },
  {
    "id": 500142,
    "desc": "角色-3-等级43",
    "role_id": 400002,
    "level": 43,
    "need_exp": 100
  },
  {
    "id": 500143,
    "desc": "角色-3-等级44",
    "role_id": 400002,
    "level": 44,
    "need_exp": 100
  },
  {
    "id": 500144,
    "desc": "角色-3-等级45",
    "role_id": 400002,
    "level": 45,
    "need_exp": 100
  },
  {
    "id": 500145,
    "desc": "角色-3-等级46",
    "role_id": 400002,
    "level": 46,
    "need_exp": 100
  },
  {
    "id": 500146,
    "desc": "角色-3-等级47",
    "role_id": 400002,
    "level": 47,
    "need_exp": 100
  },
  {
    "id": 500147,
    "desc": "角色-3-等级48",
    "role_id": 400002,
    "level": 48,
    "need_exp": 100
  },
  {
    "id": 500148,
    "desc": "角色-3-等级49",
    "role_id": 400002,
    "level": 49,
    "need_exp": 100
  },
  {
    "id": 500149,
    "desc": "角色-3-等级50",
    "role_id": 400002,
    "level": 50,
    "need_exp": 100
  },
  {
    "id": 500150,
    "desc": "角色-4-等级1",
    "role_id": 400003,
    "level": 1,
    "need_exp": 100
  },
  {
    "id": 500151,
    "desc": "角色-4-等级2",
    "role_id": 400003,
    "level": 2,
    "need_exp": 100
  },
  {
    "id": 500152,
    "desc": "角色-4-等级3",
    "role_id": 400003,
    "level": 3,
    "need_exp": 100
  },
  {
    "id": 500153,
    "desc": "角色-4-等级4",
    "role_id": 400003,
    "level": 4,
    "need_exp": 100
  },
  {
    "id": 500154,
    "desc": "角色-4-等级5",
    "role_id": 400003,
    "level": 5,
    "need_exp": 100
  },
  {
    "id": 500155,
    "desc": "角色-4-等级6",
    "role_id": 400003,
    "level": 6,
    "need_exp": 100
  },
  {
    "id": 500156,
    "desc": "角色-4-等级7",
    "role_id": 400003,
    "level": 7,
    "need_exp": 100
  },
  {
    "id": 500157,
    "desc": "角色-4-等级8",
    "role_id": 400003,
    "level": 8,
    "need_exp": 100
  },
  {
    "id": 500158,
    "desc": "角色-4-等级9",
    "role_id": 400003,
    "level": 9,
    "need_exp": 100
  },
  {
    "id": 500159,
    "desc": "角色-4-等级10",
    "role_id": 400003,
    "level": 10,
    "need_exp": 100
  },
  {
    "id": 500160,
    "desc": "角色-4-等级11",
    "role_id": 400003,
    "level": 11,
    "need_exp": 100
  },
  {
    "id": 500161,
    "desc": "角色-4-等级12",
    "role_id": 400003,
    "level": 12,
    "need_exp": 100
  },
  {
    "id": 500162,
    "desc": "角色-4-等级13",
    "role_id": 400003,
    "level": 13,
    "need_exp": 100
  },
  {
    "id": 500163,
    "desc": "角色-4-等级14",
    "role_id": 400003,
    "level": 14,
    "need_exp": 100
  },
  {
    "id": 500164,
    "desc": "角色-4-等级15",
    "role_id": 400003,
    "level": 15,
    "need_exp": 100
  },
  {
    "id": 500165,
    "desc": "角色-4-等级16",
    "role_id": 400003,
    "level": 16,
    "need_exp": 100
  },
  {
    "id": 500166,
    "desc": "角色-4-等级17",
    "role_id": 400003,
    "level": 17,
    "need_exp": 100
  },
  {
    "id": 500167,
    "desc": "角色-4-等级18",
    "role_id": 400003,
    "level": 18,
    "need_exp": 100
  },
  {
    "id": 500168,
    "desc": "角色-4-等级19",
    "role_id": 400003,
    "level": 19,
    "need_exp": 100
  },
  {
    "id": 500169,
    "desc": "角色-4-等级20",
    "role_id": 400003,
    "level": 20,
    "need_exp": 100
  },
  {
    "id": 500170,
    "desc": "角色-4-等级21",
    "role_id": 400003,
    "level": 21,
    "need_exp": 100
  },
  {
    "id": 500171,
    "desc": "角色-4-等级22",
    "role_id": 400003,
    "level": 22,
    "need_exp": 100
  },
  {
    "id": 500172,
    "desc": "角色-4-等级23",
    "role_id": 400003,
    "level": 23,
    "need_exp": 100
  },
  {
    "id": 500173,
    "desc": "角色-4-等级24",
    "role_id": 400003,
    "level": 24,
    "need_exp": 100
  },
  {
    "id": 500174,
    "desc": "角色-4-等级25",
    "role_id": 400003,
    "level": 25,
    "need_exp": 100
  },
  {
    "id": 500175,
    "desc": "角色-4-等级26",
    "role_id": 400003,
    "level": 26,
    "need_exp": 100
  },
  {
    "id": 500176,
    "desc": "角色-4-等级27",
    "role_id": 400003,
    "level": 27,
    "need_exp": 100
  },
  {
    "id": 500177,
    "desc": "角色-4-等级28",
    "role_id": 400003,
    "level": 28,
    "need_exp": 100
  },
  {
    "id": 500178,
    "desc": "角色-4-等级29",
    "role_id": 400003,
    "level": 29,
    "need_exp": 100
  },
  {
    "id": 500179,
    "desc": "角色-4-等级30",
    "role_id": 400003,
    "level": 30,
    "need_exp": 100
  },
  {
    "id": 500180,
    "desc": "角色-4-等级31",
    "role_id": 400003,
    "level": 31,
    "need_exp": 100
  },
  {
    "id": 500181,
    "desc": "角色-4-等级32",
    "role_id": 400003,
    "level": 32,
    "need_exp": 100
  },
  {
    "id": 500182,
    "desc": "角色-4-等级33",
    "role_id": 400003,
    "level": 33,
    "need_exp": 100
  },
  {
    "id": 500183,
    "desc": "角色-4-等级34",
    "role_id": 400003,
    "level": 34,
    "need_exp": 100
  },
  {
    "id": 500184,
    "desc": "角色-4-等级35",
    "role_id": 400003,
    "level": 35,
    "need_exp": 100
  },
  {
    "id": 500185,
    "desc": "角色-4-等级36",
    "role_id": 400003,
    "level": 36,
    "need_exp": 100
  },
  {
    "id": 500186,
    "desc": "角色-4-等级37",
    "role_id": 400003,
    "level": 37,
    "need_exp": 100
  },
  {
    "id": 500187,
    "desc": "角色-4-等级38",
    "role_id": 400003,
    "level": 38,
    "need_exp": 100
  },
  {
    "id": 500188,
    "desc": "角色-4-等级39",
    "role_id": 400003,
    "level": 39,
    "need_exp": 100
  },
  {
    "id": 500189,
    "desc": "角色-4-等级40",
    "role_id": 400003,
    "level": 40,
    "need_exp": 100
  },
  {
    "id": 500190,
    "desc": "角色-4-等级41",
    "role_id": 400003,
    "level": 41,
    "need_exp": 100
  },
  {
    "id": 500191,
    "desc": "角色-4-等级42",
    "role_id": 400003,
    "level": 42,
    "need_exp": 100
  },
  {
    "id": 500192,
    "desc": "角色-4-等级43",
    "role_id": 400003,
    "level": 43,
    "need_exp": 100
  },
  {
    "id": 500193,
    "desc": "角色-4-等级44",
    "role_id": 400003,
    "level": 44,
    "need_exp": 100
  },
  {
    "id": 500194,
    "desc": "角色-4-等级45",
    "role_id": 400003,
    "level": 45,
    "need_exp": 100
  },
  {
    "id": 500195,
    "desc": "角色-4-等级46",
    "role_id": 400003,
    "level": 46,
    "need_exp": 100
  },
  {
    "id": 500196,
    "desc": "角色-4-等级47",
    "role_id": 400003,
    "level": 47,
    "need_exp": 100
  },
  {
    "id": 500197,
    "desc": "角色-4-等级48",
    "role_id": 400003,
    "level": 48,
    "need_exp": 100
  },
  {
    "id": 500198,
    "desc": "角色-4-等级49",
    "role_id": 400003,
    "level": 49,
    "need_exp": 100
  },
  {
    "id": 500199,
    "desc": "角色-4-等级50",
    "role_id": 400003,
    "level": 50,
    "need_exp": 100
  },
  {
    "id": 500200,
    "desc": "角色-5-等级1",
    "role_id": 400004,
    "level": 1,
    "need_exp": 100
  },
  {
    "id": 500201,
    "desc": "角色-5-等级2",
    "role_id": 400004,
    "level": 2,
    "need_exp": 100
  },
  {
    "id": 500202,
    "desc": "角色-5-等级3",
    "role_id": 400004,
    "level": 3,
    "need_exp": 100
  },
  {
    "id": 500203,
    "desc": "角色-5-等级4",
    "role_id": 400004,
    "level": 4,
    "need_exp": 100
  },
  {
    "id": 500204,
    "desc": "角色-5-等级5",
    "role_id": 400004,
    "level": 5,
    "need_exp": 100
  },
  {
    "id": 500205,
    "desc": "角色-5-等级6",
    "role_id": 400004,
    "level": 6,
    "need_exp": 100
  },
  {
    "id": 500206,
    "desc": "角色-5-等级7",
    "role_id": 400004,
    "level": 7,
    "need_exp": 100
  },
  {
    "id": 500207,
    "desc": "角色-5-等级8",
    "role_id": 400004,
    "level": 8,
    "need_exp": 100
  },
  {
    "id": 500208,
    "desc": "角色-5-等级9",
    "role_id": 400004,
    "level": 9,
    "need_exp": 100
  },
  {
    "id": 500209,
    "desc": "角色-5-等级10",
    "role_id": 400004,
    "level": 10,
    "need_exp": 100
  },
  {
    "id": 500210,
    "desc": "角色-5-等级11",
    "role_id": 400004,
    "level": 11,
    "need_exp": 100
  },
  {
    "id": 500211,
    "desc": "角色-5-等级12",
    "role_id": 400004,
    "level": 12,
    "need_exp": 100
  },
  {
    "id": 500212,
    "desc": "角色-5-等级13",
    "role_id": 400004,
    "level": 13,
    "need_exp": 100
  },
  {
    "id": 500213,
    "desc": "角色-5-等级14",
    "role_id": 400004,
    "level": 14,
    "need_exp": 100
  },
  {
    "id": 500214,
    "desc": "角色-5-等级15",
    "role_id": 400004,
    "level": 15,
    "need_exp": 100
  },
  {
    "id": 500215,
    "desc": "角色-5-等级16",
    "role_id": 400004,
    "level": 16,
    "need_exp": 100
  },
  {
    "id": 500216,
    "desc": "角色-5-等级17",
    "role_id": 400004,
    "level": 17,
    "need_exp": 100
  },
  {
    "id": 500217,
    "desc": "角色-5-等级18",
    "role_id": 400004,
    "level": 18,
    "need_exp": 100
  },
  {
    "id": 500218,
    "desc": "角色-5-等级19",
    "role_id": 400004,
    "level": 19,
    "need_exp": 100
  },
  {
    "id": 500219,
    "desc": "角色-5-等级20",
    "role_id": 400004,
    "level": 20,
    "need_exp": 100
  },
  {
    "id": 500220,
    "desc": "角色-5-等级21",
    "role_id": 400004,
    "level": 21,
    "need_exp": 100
  },
  {
    "id": 500221,
    "desc": "角色-5-等级22",
    "role_id": 400004,
    "level": 22,
    "need_exp": 100
  },
  {
    "id": 500222,
    "desc": "角色-5-等级23",
    "role_id": 400004,
    "level": 23,
    "need_exp": 100
  },
  {
    "id": 500223,
    "desc": "角色-5-等级24",
    "role_id": 400004,
    "level": 24,
    "need_exp": 100
  },
  {
    "id": 500224,
    "desc": "角色-5-等级25",
    "role_id": 400004,
    "level": 25,
    "need_exp": 100
  },
  {
    "id": 500225,
    "desc": "角色-5-等级26",
    "role_id": 400004,
    "level": 26,
    "need_exp": 100
  },
  {
    "id": 500226,
    "desc": "角色-5-等级27",
    "role_id": 400004,
    "level": 27,
    "need_exp": 100
  },
  {
    "id": 500227,
    "desc": "角色-5-等级28",
    "role_id": 400004,
    "level": 28,
    "need_exp": 100
  },
  {
    "id": 500228,
    "desc": "角色-5-等级29",
    "role_id": 400004,
    "level": 29,
    "need_exp": 100
  },
  {
    "id": 500229,
    "desc": "角色-5-等级30",
    "role_id": 400004,
    "level": 30,
    "need_exp": 100
  },
  {
    "id": 500230,
    "desc": "角色-5-等级31",
    "role_id": 400004,
    "level": 31,
    "need_exp": 100
  },
  {
    "id": 500231,
    "desc": "角色-5-等级32",
    "role_id": 400004,
    "level": 32,
    "need_exp": 100
  },
  {
    "id": 500232,
    "desc": "角色-5-等级33",
    "role_id": 400004,
    "level": 33,
    "need_exp": 100
  },
  {
    "id": 500233,
    "desc": "角色-5-等级34",
    "role_id": 400004,
    "level": 34,
    "need_exp": 100
  },
  {
    "id": 500234,
    "desc": "角色-5-等级35",
    "role_id": 400004,
    "level": 35,
    "need_exp": 100
  },
  {
    "id": 500235,
    "desc": "角色-5-等级36",
    "role_id": 400004,
    "level": 36,
    "need_exp": 100
  },
  {
    "id": 500236,
    "desc": "角色-5-等级37",
    "role_id": 400004,
    "level": 37,
    "need_exp": 100
  },
  {
    "id": 500237,
    "desc": "角色-5-等级38",
    "role_id": 400004,
    "level": 38,
    "need_exp": 100
  },
  {
    "id": 500238,
    "desc": "角色-5-等级39",
    "role_id": 400004,
    "level": 39,
    "need_exp": 100
  },
  {
    "id": 500239,
    "desc": "角色-5-等级40",
    "role_id": 400004,
    "level": 40,
    "need_exp": 100
  },
  {
    "id": 500240,
    "desc": "角色-5-等级41",
    "role_id": 400004,
    "level": 41,
    "need_exp": 100
  },
  {
    "id": 500241,
    "desc": "角色-5-等级42",
    "role_id": 400004,
    "level": 42,
    "need_exp": 100
  },
  {
    "id": 500242,
    "desc": "角色-5-等级43",
    "role_id": 400004,
    "level": 43,
    "need_exp": 100
  },
  {
    "id": 500243,
    "desc": "角色-5-等级44",
    "role_id": 400004,
    "level": 44,
    "need_exp": 100
  },
  {
    "id": 500244,
    "desc": "角色-5-等级45",
    "role_id": 400004,
    "level": 45,
    "need_exp": 100
  },
  {
    "id": 500245,
    "desc": "角色-5-等级46",
    "role_id": 400004,
    "level": 46,
    "need_exp": 100
  },
  {
    "id": 500246,
    "desc": "角色-5-等级47",
    "role_id": 400004,
    "level": 47,
    "need_exp": 100
  },
  {
    "id": 500247,
    "desc": "角色-5-等级48",
    "role_id": 400004,
    "level": 48,
    "need_exp": 100
  },
  {
    "id": 500248,
    "desc": "角色-5-等级49",
    "role_id": 400004,
    "level": 49,
    "need_exp": 100
  },
  {
    "id": 500249,
    "desc": "角色-5-等级50",
    "role_id": 400004,
    "level": 50,
    "need_exp": 100
  },
  {
    "id": 500250,
    "desc": "角色-6-等级1",
    "role_id": 400005,
    "level": 1,
    "need_exp": 100
  },
  {
    "id": 500251,
    "desc": "角色-6-等级2",
    "role_id": 400005,
    "level": 2,
    "need_exp": 100
  },
  {
    "id": 500252,
    "desc": "角色-6-等级3",
    "role_id": 400005,
    "level": 3,
    "need_exp": 100
  },
  {
    "id": 500253,
    "desc": "角色-6-等级4",
    "role_id": 400005,
    "level": 4,
    "need_exp": 100
  },
  {
    "id": 500254,
    "desc": "角色-6-等级5",
    "role_id": 400005,
    "level": 5,
    "need_exp": 100
  },
  {
    "id": 500255,
    "desc": "角色-6-等级6",
    "role_id": 400005,
    "level": 6,
    "need_exp": 100
  },
  {
    "id": 500256,
    "desc": "角色-6-等级7",
    "role_id": 400005,
    "level": 7,
    "need_exp": 100
  },
  {
    "id": 500257,
    "desc": "角色-6-等级8",
    "role_id": 400005,
    "level": 8,
    "need_exp": 100
  },
  {
    "id": 500258,
    "desc": "角色-6-等级9",
    "role_id": 400005,
    "level": 9,
    "need_exp": 100
  },
  {
    "id": 500259,
    "desc": "角色-6-等级10",
    "role_id": 400005,
    "level": 10,
    "need_exp": 100
  },
  {
    "id": 500260,
    "desc": "角色-6-等级11",
    "role_id": 400005,
    "level": 11,
    "need_exp": 100
  },
  {
    "id": 500261,
    "desc": "角色-6-等级12",
    "role_id": 400005,
    "level": 12,
    "need_exp": 100
  },
  {
    "id": 500262,
    "desc": "角色-6-等级13",
    "role_id": 400005,
    "level": 13,
    "need_exp": 100
  },
  {
    "id": 500263,
    "desc": "角色-6-等级14",
    "role_id": 400005,
    "level": 14,
    "need_exp": 100
  },
  {
    "id": 500264,
    "desc": "角色-6-等级15",
    "role_id": 400005,
    "level": 15,
    "need_exp": 100
  },
  {
    "id": 500265,
    "desc": "角色-6-等级16",
    "role_id": 400005,
    "level": 16,
    "need_exp": 100
  },
  {
    "id": 500266,
    "desc": "角色-6-等级17",
    "role_id": 400005,
    "level": 17,
    "need_exp": 100
  },
  {
    "id": 500267,
    "desc": "角色-6-等级18",
    "role_id": 400005,
    "level": 18,
    "need_exp": 100
  },
  {
    "id": 500268,
    "desc": "角色-6-等级19",
    "role_id": 400005,
    "level": 19,
    "need_exp": 100
  },
  {
    "id": 500269,
    "desc": "角色-6-等级20",
    "role_id": 400005,
    "level": 20,
    "need_exp": 100
  },
  {
    "id": 500270,
    "desc": "角色-6-等级21",
    "role_id": 400005,
    "level": 21,
    "need_exp": 100
  },
  {
    "id": 500271,
    "desc": "角色-6-等级22",
    "role_id": 400005,
    "level": 22,
    "need_exp": 100
  },
  {
    "id": 500272,
    "desc": "角色-6-等级23",
    "role_id": 400005,
    "level": 23,
    "need_exp": 100
  },
  {
    "id": 500273,
    "desc": "角色-6-等级24",
    "role_id": 400005,
    "level": 24,
    "need_exp": 100
  },
  {
    "id": 500274,
    "desc": "角色-6-等级25",
    "role_id": 400005,
    "level": 25,
    "need_exp": 100
  },
  {
    "id": 500275,
    "desc": "角色-6-等级26",
    "role_id": 400005,
    "level": 26,
    "need_exp": 100
  },
  {
    "id": 500276,
    "desc": "角色-6-等级27",
    "role_id": 400005,
    "level": 27,
    "need_exp": 100
  },
  {
    "id": 500277,
    "desc": "角色-6-等级28",
    "role_id": 400005,
    "level": 28,
    "need_exp": 100
  },
  {
    "id": 500278,
    "desc": "角色-6-等级29",
    "role_id": 400005,
    "level": 29,
    "need_exp": 100
  },
  {
    "id": 500279,
    "desc": "角色-6-等级30",
    "role_id": 400005,
    "level": 30,
    "need_exp": 100
  },
  {
    "id": 500280,
    "desc": "角色-6-等级31",
    "role_id": 400005,
    "level": 31,
    "need_exp": 100
  },
  {
    "id": 500281,
    "desc": "角色-6-等级32",
    "role_id": 400005,
    "level": 32,
    "need_exp": 100
  },
  {
    "id": 500282,
    "desc": "角色-6-等级33",
    "role_id": 400005,
    "level": 33,
    "need_exp": 100
  },
  {
    "id": 500283,
    "desc": "角色-6-等级34",
    "role_id": 400005,
    "level": 34,
    "need_exp": 100
  },
  {
    "id": 500284,
    "desc": "角色-6-等级35",
    "role_id": 400005,
    "level": 35,
    "need_exp": 100
  },
  {
    "id": 500285,
    "desc": "角色-6-等级36",
    "role_id": 400005,
    "level": 36,
    "need_exp": 100
  },
  {
    "id": 500286,
    "desc": "角色-6-等级37",
    "role_id": 400005,
    "level": 37,
    "need_exp": 100
  },
  {
    "id": 500287,
    "desc": "角色-6-等级38",
    "role_id": 400005,
    "level": 38,
    "need_exp": 100
  },
  {
    "id": 500288,
    "desc": "角色-6-等级39",
    "role_id": 400005,
    "level": 39,
    "need_exp": 100
  },
  {
    "id": 500289,
    "desc": "角色-6-等级40",
    "role_id": 400005,
    "level": 40,
    "need_exp": 100
  },
  {
    "id": 500290,
    "desc": "角色-6-等级41",
    "role_id": 400005,
    "level": 41,
    "need_exp": 100
  },
  {
    "id": 500291,
    "desc": "角色-6-等级42",
    "role_id": 400005,
    "level": 42,
    "need_exp": 100
  },
  {
    "id": 500292,
    "desc": "角色-6-等级43",
    "role_id": 400005,
    "level": 43,
    "need_exp": 100
  },
  {
    "id": 500293,
    "desc": "角色-6-等级44",
    "role_id": 400005,
    "level": 44,
    "need_exp": 100
  },
  {
    "id": 500294,
    "desc": "角色-6-等级45",
    "role_id": 400005,
    "level": 45,
    "need_exp": 100
  },
  {
    "id": 500295,
    "desc": "角色-6-等级46",
    "role_id": 400005,
    "level": 46,
    "need_exp": 100
  },
  {
    "id": 500296,
    "desc": "角色-6-等级47",
    "role_id": 400005,
    "level": 47,
    "need_exp": 100
  },
  {
    "id": 500297,
    "desc": "角色-6-等级48",
    "role_id": 400005,
    "level": 48,
    "need_exp": 100
  },
  {
    "id": 500298,
    "desc": "角色-6-等级49",
    "role_id": 400005,
    "level": 49,
    "need_exp": 100
  },
  {
    "id": 500299,
    "desc": "角色-6-等级50",
    "role_id": 400005,
    "level": 50,
    "need_exp": 100
  },
  {
    "id": 500300,
    "desc": "角色-7-等级1",
    "role_id": 400006,
    "level": 1,
    "need_exp": 100
  },
  {
    "id": 500301,
    "desc": "角色-7-等级2",
    "role_id": 400006,
    "level": 2,
    "need_exp": 100
  },
  {
    "id": 500302,
    "desc": "角色-7-等级3",
    "role_id": 400006,
    "level": 3,
    "need_exp": 100
  },
  {
    "id": 500303,
    "desc": "角色-7-等级4",
    "role_id": 400006,
    "level": 4,
    "need_exp": 100
  },
  {
    "id": 500304,
    "desc": "角色-7-等级5",
    "role_id": 400006,
    "level": 5,
    "need_exp": 100
  },
  {
    "id": 500305,
    "desc": "角色-7-等级6",
    "role_id": 400006,
    "level": 6,
    "need_exp": 100
  },
  {
    "id": 500306,
    "desc": "角色-7-等级7",
    "role_id": 400006,
    "level": 7,
    "need_exp": 100
  },
  {
    "id": 500307,
    "desc": "角色-7-等级8",
    "role_id": 400006,
    "level": 8,
    "need_exp": 100
  },
  {
    "id": 500308,
    "desc": "角色-7-等级9",
    "role_id": 400006,
    "level": 9,
    "need_exp": 100
  },
  {
    "id": 500309,
    "desc": "角色-7-等级10",
    "role_id": 400006,
    "level": 10,
    "need_exp": 100
  },
  {
    "id": 500310,
    "desc": "角色-7-等级11",
    "role_id": 400006,
    "level": 11,
    "need_exp": 100
  },
  {
    "id": 500311,
    "desc": "角色-7-等级12",
    "role_id": 400006,
    "level": 12,
    "need_exp": 100
  },
  {
    "id": 500312,
    "desc": "角色-7-等级13",
    "role_id": 400006,
    "level": 13,
    "need_exp": 100
  },
  {
    "id": 500313,
    "desc": "角色-7-等级14",
    "role_id": 400006,
    "level": 14,
    "need_exp": 100
  },
  {
    "id": 500314,
    "desc": "角色-7-等级15",
    "role_id": 400006,
    "level": 15,
    "need_exp": 100
  },
  {
    "id": 500315,
    "desc": "角色-7-等级16",
    "role_id": 400006,
    "level": 16,
    "need_exp": 100
  },
  {
    "id": 500316,
    "desc": "角色-7-等级17",
    "role_id": 400006,
    "level": 17,
    "need_exp": 100
  },
  {
    "id": 500317,
    "desc": "角色-7-等级18",
    "role_id": 400006,
    "level": 18,
    "need_exp": 100
  },
  {
    "id": 500318,
    "desc": "角色-7-等级19",
    "role_id": 400006,
    "level": 19,
    "need_exp": 100
  },
  {
    "id": 500319,
    "desc": "角色-7-等级20",
    "role_id": 400006,
    "level": 20,
    "need_exp": 100
  },
  {
    "id": 500320,
    "desc": "角色-7-等级21",
    "role_id": 400006,
    "level": 21,
    "need_exp": 100
  },
  {
    "id": 500321,
    "desc": "角色-7-等级22",
    "role_id": 400006,
    "level": 22,
    "need_exp": 100
  },
  {
    "id": 500322,
    "desc": "角色-7-等级23",
    "role_id": 400006,
    "level": 23,
    "need_exp": 100
  },
  {
    "id": 500323,
    "desc": "角色-7-等级24",
    "role_id": 400006,
    "level": 24,
    "need_exp": 100
  },
  {
    "id": 500324,
    "desc": "角色-7-等级25",
    "role_id": 400006,
    "level": 25,
    "need_exp": 100
  },
  {
    "id": 500325,
    "desc": "角色-7-等级26",
    "role_id": 400006,
    "level": 26,
    "need_exp": 100
  },
  {
    "id": 500326,
    "desc": "角色-7-等级27",
    "role_id": 400006,
    "level": 27,
    "need_exp": 100
  },
  {
    "id": 500327,
    "desc": "角色-7-等级28",
    "role_id": 400006,
    "level": 28,
    "need_exp": 100
  },
  {
    "id": 500328,
    "desc": "角色-7-等级29",
    "role_id": 400006,
    "level": 29,
    "need_exp": 100
  },
  {
    "id": 500329,
    "desc": "角色-7-等级30",
    "role_id": 400006,
    "level": 30,
    "need_exp": 100
  },
  {
    "id": 500330,
    "desc": "角色-7-等级31",
    "role_id": 400006,
    "level": 31,
    "need_exp": 100
  },
  {
    "id": 500331,
    "desc": "角色-7-等级32",
    "role_id": 400006,
    "level": 32,
    "need_exp": 100
  },
  {
    "id": 500332,
    "desc": "角色-7-等级33",
    "role_id": 400006,
    "level": 33,
    "need_exp": 100
  },
  {
    "id": 500333,
    "desc": "角色-7-等级34",
    "role_id": 400006,
    "level": 34,
    "need_exp": 100
  },
  {
    "id": 500334,
    "desc": "角色-7-等级35",
    "role_id": 400006,
    "level": 35,
    "need_exp": 100
  },
  {
    "id": 500335,
    "desc": "角色-7-等级36",
    "role_id": 400006,
    "level": 36,
    "need_exp": 100
  },
  {
    "id": 500336,
    "desc": "角色-7-等级37",
    "role_id": 400006,
    "level": 37,
    "need_exp": 100
  },
  {
    "id": 500337,
    "desc": "角色-7-等级38",
    "role_id": 400006,
    "level": 38,
    "need_exp": 100
  },
  {
    "id": 500338,
    "desc": "角色-7-等级39",
    "role_id": 400006,
    "level": 39,
    "need_exp": 100
  },
  {
    "id": 500339,
    "desc": "角色-7-等级40",
    "role_id": 400006,
    "level": 40,
    "need_exp": 100
  },
  {
    "id": 500340,
    "desc": "角色-7-等级41",
    "role_id": 400006,
    "level": 41,
    "need_exp": 100
  },
  {
    "id": 500341,
    "desc": "角色-7-等级42",
    "role_id": 400006,
    "level": 42,
    "need_exp": 100
  },
  {
    "id": 500342,
    "desc": "角色-7-等级43",
    "role_id": 400006,
    "level": 43,
    "need_exp": 100
  },
  {
    "id": 500343,
    "desc": "角色-7-等级44",
    "role_id": 400006,
    "level": 44,
    "need_exp": 100
  },
  {
    "id": 500344,
    "desc": "角色-7-等级45",
    "role_id": 400006,
    "level": 45,
    "need_exp": 100
  },
  {
    "id": 500345,
    "desc": "角色-7-等级46",
    "role_id": 400006,
    "level": 46,
    "need_exp": 100
  },
  {
    "id": 500346,
    "desc": "角色-7-等级47",
    "role_id": 400006,
    "level": 47,
    "need_exp": 100
  },
  {
    "id": 500347,
    "desc": "角色-7-等级48",
    "role_id": 400006,
    "level": 48,
    "need_exp": 100
  },
  {
    "id": 500348,
    "desc": "角色-7-等级49",
    "role_id": 400006,
    "level": 49,
    "need_exp": 100
  },
  {
    "id": 500349,
    "desc": "角色-7-等级50",
    "role_id": 400006,
    "level": 50,
    "need_exp": 100
  },
  {
    "id": 500350,
    "desc": "角色-8-等级1",
    "role_id": 400007,
    "level": 1,
    "need_exp": 100
  },
  {
    "id": 500351,
    "desc": "角色-8-等级2",
    "role_id": 400007,
    "level": 2,
    "need_exp": 100
  },
  {
    "id": 500352,
    "desc": "角色-8-等级3",
    "role_id": 400007,
    "level": 3,
    "need_exp": 100
  },
  {
    "id": 500353,
    "desc": "角色-8-等级4",
    "role_id": 400007,
    "level": 4,
    "need_exp": 100
  },
  {
    "id": 500354,
    "desc": "角色-8-等级5",
    "role_id": 400007,
    "level": 5,
    "need_exp": 100
  },
  {
    "id": 500355,
    "desc": "角色-8-等级6",
    "role_id": 400007,
    "level": 6,
    "need_exp": 100
  },
  {
    "id": 500356,
    "desc": "角色-8-等级7",
    "role_id": 400007,
    "level": 7,
    "need_exp": 100
  },
  {
    "id": 500357,
    "desc": "角色-8-等级8",
    "role_id": 400007,
    "level": 8,
    "need_exp": 100
  },
  {
    "id": 500358,
    "desc": "角色-8-等级9",
    "role_id": 400007,
    "level": 9,
    "need_exp": 100
  },
  {
    "id": 500359,
    "desc": "角色-8-等级10",
    "role_id": 400007,
    "level": 10,
    "need_exp": 100
  },
  {
    "id": 500360,
    "desc": "角色-8-等级11",
    "role_id": 400007,
    "level": 11,
    "need_exp": 100
  },
  {
    "id": 500361,
    "desc": "角色-8-等级12",
    "role_id": 400007,
    "level": 12,
    "need_exp": 100
  },
  {
    "id": 500362,
    "desc": "角色-8-等级13",
    "role_id": 400007,
    "level": 13,
    "need_exp": 100
  },
  {
    "id": 500363,
    "desc": "角色-8-等级14",
    "role_id": 400007,
    "level": 14,
    "need_exp": 100
  },
  {
    "id": 500364,
    "desc": "角色-8-等级15",
    "role_id": 400007,
    "level": 15,
    "need_exp": 100
  },
  {
    "id": 500365,
    "desc": "角色-8-等级16",
    "role_id": 400007,
    "level": 16,
    "need_exp": 100
  },
  {
    "id": 500366,
    "desc": "角色-8-等级17",
    "role_id": 400007,
    "level": 17,
    "need_exp": 100
  },
  {
    "id": 500367,
    "desc": "角色-8-等级18",
    "role_id": 400007,
    "level": 18,
    "need_exp": 100
  },
  {
    "id": 500368,
    "desc": "角色-8-等级19",
    "role_id": 400007,
    "level": 19,
    "need_exp": 100
  },
  {
    "id": 500369,
    "desc": "角色-8-等级20",
    "role_id": 400007,
    "level": 20,
    "need_exp": 100
  },
  {
    "id": 500370,
    "desc": "角色-8-等级21",
    "role_id": 400007,
    "level": 21,
    "need_exp": 100
  },
  {
    "id": 500371,
    "desc": "角色-8-等级22",
    "role_id": 400007,
    "level": 22,
    "need_exp": 100
  },
  {
    "id": 500372,
    "desc": "角色-8-等级23",
    "role_id": 400007,
    "level": 23,
    "need_exp": 100
  },
  {
    "id": 500373,
    "desc": "角色-8-等级24",
    "role_id": 400007,
    "level": 24,
    "need_exp": 100
  },
  {
    "id": 500374,
    "desc": "角色-8-等级25",
    "role_id": 400007,
    "level": 25,
    "need_exp": 100
  },
  {
    "id": 500375,
    "desc": "角色-8-等级26",
    "role_id": 400007,
    "level": 26,
    "need_exp": 100
  },
  {
    "id": 500376,
    "desc": "角色-8-等级27",
    "role_id": 400007,
    "level": 27,
    "need_exp": 100
  },
  {
    "id": 500377,
    "desc": "角色-8-等级28",
    "role_id": 400007,
    "level": 28,
    "need_exp": 100
  },
  {
    "id": 500378,
    "desc": "角色-8-等级29",
    "role_id": 400007,
    "level": 29,
    "need_exp": 100
  },
  {
    "id": 500379,
    "desc": "角色-8-等级30",
    "role_id": 400007,
    "level": 30,
    "need_exp": 100
  },
  {
    "id": 500380,
    "desc": "角色-8-等级31",
    "role_id": 400007,
    "level": 31,
    "need_exp": 100
  },
  {
    "id": 500381,
    "desc": "角色-8-等级32",
    "role_id": 400007,
    "level": 32,
    "need_exp": 100
  },
  {
    "id": 500382,
    "desc": "角色-8-等级33",
    "role_id": 400007,
    "level": 33,
    "need_exp": 100
  },
  {
    "id": 500383,
    "desc": "角色-8-等级34",
    "role_id": 400007,
    "level": 34,
    "need_exp": 100
  },
  {
    "id": 500384,
    "desc": "角色-8-等级35",
    "role_id": 400007,
    "level": 35,
    "need_exp": 100
  },
  {
    "id": 500385,
    "desc": "角色-8-等级36",
    "role_id": 400007,
    "level": 36,
    "need_exp": 100
  },
  {
    "id": 500386,
    "desc": "角色-8-等级37",
    "role_id": 400007,
    "level": 37,
    "need_exp": 100
  },
  {
    "id": 500387,
    "desc": "角色-8-等级38",
    "role_id": 400007,
    "level": 38,
    "need_exp": 100
  },
  {
    "id": 500388,
    "desc": "角色-8-等级39",
    "role_id": 400007,
    "level": 39,
    "need_exp": 100
  },
  {
    "id": 500389,
    "desc": "角色-8-等级40",
    "role_id": 400007,
    "level": 40,
    "need_exp": 100
  },
  {
    "id": 500390,
    "desc": "角色-8-等级41",
    "role_id": 400007,
    "level": 41,
    "need_exp": 100
  },
  {
    "id": 500391,
    "desc": "角色-8-等级42",
    "role_id": 400007,
    "level": 42,
    "need_exp": 100
  },
  {
    "id": 500392,
    "desc": "角色-8-等级43",
    "role_id": 400007,
    "level": 43,
    "need_exp": 100
  },
  {
    "id": 500393,
    "desc": "角色-8-等级44",
    "role_id": 400007,
    "level": 44,
    "need_exp": 100
  },
  {
    "id": 500394,
    "desc": "角色-8-等级45",
    "role_id": 400007,
    "level": 45,
    "need_exp": 100
  },
  {
    "id": 500395,
    "desc": "角色-8-等级46",
    "role_id": 400007,
    "level": 46,
    "need_exp": 100
  },
  {
    "id": 500396,
    "desc": "角色-8-等级47",
    "role_id": 400007,
    "level": 47,
    "need_exp": 100
  },
  {
    "id": 500397,
    "desc": "角色-8-等级48",
    "role_id": 400007,
    "level": 48,
    "need_exp": 100
  },
  {
    "id": 500398,
    "desc": "角色-8-等级49",
    "role_id": 400007,
    "level": 49,
    "need_exp": 100
  },
  {
    "id": 500399,
    "desc": "角色-8-等级50",
    "role_id": 400007,
    "level": 50,
    "need_exp": 100
  },
  {
    "id": 500400,
    "desc": "角色-9-等级1",
    "role_id": 400008,
    "level": 1,
    "need_exp": 100
  },
  {
    "id": 500401,
    "desc": "角色-9-等级2",
    "role_id": 400008,
    "level": 2,
    "need_exp": 100
  },
  {
    "id": 500402,
    "desc": "角色-9-等级3",
    "role_id": 400008,
    "level": 3,
    "need_exp": 100
  },
  {
    "id": 500403,
    "desc": "角色-9-等级4",
    "role_id": 400008,
    "level": 4,
    "need_exp": 100
  },
  {
    "id": 500404,
    "desc": "角色-9-等级5",
    "role_id": 400008,
    "level": 5,
    "need_exp": 100
  },
  {
    "id": 500405,
    "desc": "角色-9-等级6",
    "role_id": 400008,
    "level": 6,
    "need_exp": 100
  },
  {
    "id": 500406,
    "desc": "角色-9-等级7",
    "role_id": 400008,
    "level": 7,
    "need_exp": 100
  },
  {
    "id": 500407,
    "desc": "角色-9-等级8",
    "role_id": 400008,
    "level": 8,
    "need_exp": 100
  },
  {
    "id": 500408,
    "desc": "角色-9-等级9",
    "role_id": 400008,
    "level": 9,
    "need_exp": 100
  },
  {
    "id": 500409,
    "desc": "角色-9-等级10",
    "role_id": 400008,
    "level": 10,
    "need_exp": 100
  },
  {
    "id": 500410,
    "desc": "角色-9-等级11",
    "role_id": 400008,
    "level": 11,
    "need_exp": 100
  },
  {
    "id": 500411,
    "desc": "角色-9-等级12",
    "role_id": 400008,
    "level": 12,
    "need_exp": 100
  },
  {
    "id": 500412,
    "desc": "角色-9-等级13",
    "role_id": 400008,
    "level": 13,
    "need_exp": 100
  },
  {
    "id": 500413,
    "desc": "角色-9-等级14",
    "role_id": 400008,
    "level": 14,
    "need_exp": 100
  },
  {
    "id": 500414,
    "desc": "角色-9-等级15",
    "role_id": 400008,
    "level": 15,
    "need_exp": 100
  },
  {
    "id": 500415,
    "desc": "角色-9-等级16",
    "role_id": 400008,
    "level": 16,
    "need_exp": 100
  },
  {
    "id": 500416,
    "desc": "角色-9-等级17",
    "role_id": 400008,
    "level": 17,
    "need_exp": 100
  },
  {
    "id": 500417,
    "desc": "角色-9-等级18",
    "role_id": 400008,
    "level": 18,
    "need_exp": 100
  },
  {
    "id": 500418,
    "desc": "角色-9-等级19",
    "role_id": 400008,
    "level": 19,
    "need_exp": 100
  },
  {
    "id": 500419,
    "desc": "角色-9-等级20",
    "role_id": 400008,
    "level": 20,
    "need_exp": 100
  },
  {
    "id": 500420,
    "desc": "角色-9-等级21",
    "role_id": 400008,
    "level": 21,
    "need_exp": 100
  },
  {
    "id": 500421,
    "desc": "角色-9-等级22",
    "role_id": 400008,
    "level": 22,
    "need_exp": 100
  },
  {
    "id": 500422,
    "desc": "角色-9-等级23",
    "role_id": 400008,
    "level": 23,
    "need_exp": 100
  },
  {
    "id": 500423,
    "desc": "角色-9-等级24",
    "role_id": 400008,
    "level": 24,
    "need_exp": 100
  },
  {
    "id": 500424,
    "desc": "角色-9-等级25",
    "role_id": 400008,
    "level": 25,
    "need_exp": 100
  },
  {
    "id": 500425,
    "desc": "角色-9-等级26",
    "role_id": 400008,
    "level": 26,
    "need_exp": 100
  },
  {
    "id": 500426,
    "desc": "角色-9-等级27",
    "role_id": 400008,
    "level": 27,
    "need_exp": 100
  },
  {
    "id": 500427,
    "desc": "角色-9-等级28",
    "role_id": 400008,
    "level": 28,
    "need_exp": 100
  },
  {
    "id": 500428,
    "desc": "角色-9-等级29",
    "role_id": 400008,
    "level": 29,
    "need_exp": 100
  },
  {
    "id": 500429,
    "desc": "角色-9-等级30",
    "role_id": 400008,
    "level": 30,
    "need_exp": 100
  },
  {
    "id": 500430,
    "desc": "角色-9-等级31",
    "role_id": 400008,
    "level": 31,
    "need_exp": 100
  },
  {
    "id": 500431,
    "desc": "角色-9-等级32",
    "role_id": 400008,
    "level": 32,
    "need_exp": 100
  },
  {
    "id": 500432,
    "desc": "角色-9-等级33",
    "role_id": 400008,
    "level": 33,
    "need_exp": 100
  },
  {
    "id": 500433,
    "desc": "角色-9-等级34",
    "role_id": 400008,
    "level": 34,
    "need_exp": 100
  },
  {
    "id": 500434,
    "desc": "角色-9-等级35",
    "role_id": 400008,
    "level": 35,
    "need_exp": 100
  },
  {
    "id": 500435,
    "desc": "角色-9-等级36",
    "role_id": 400008,
    "level": 36,
    "need_exp": 100
  },
  {
    "id": 500436,
    "desc": "角色-9-等级37",
    "role_id": 400008,
    "level": 37,
    "need_exp": 100
  },
  {
    "id": 500437,
    "desc": "角色-9-等级38",
    "role_id": 400008,
    "level": 38,
    "need_exp": 100
  },
  {
    "id": 500438,
    "desc": "角色-9-等级39",
    "role_id": 400008,
    "level": 39,
    "need_exp": 100
  },
  {
    "id": 500439,
    "desc": "角色-9-等级40",
    "role_id": 400008,
    "level": 40,
    "need_exp": 100
  },
  {
    "id": 500440,
    "desc": "角色-9-等级41",
    "role_id": 400008,
    "level": 41,
    "need_exp": 100
  },
  {
    "id": 500441,
    "desc": "角色-9-等级42",
    "role_id": 400008,
    "level": 42,
    "need_exp": 100
  },
  {
    "id": 500442,
    "desc": "角色-9-等级43",
    "role_id": 400008,
    "level": 43,
    "need_exp": 100
  },
  {
    "id": 500443,
    "desc": "角色-9-等级44",
    "role_id": 400008,
    "level": 44,
    "need_exp": 100
  },
  {
    "id": 500444,
    "desc": "角色-9-等级45",
    "role_id": 400008,
    "level": 45,
    "need_exp": 100
  },
  {
    "id": 500445,
    "desc": "角色-9-等级46",
    "role_id": 400008,
    "level": 46,
    "need_exp": 100
  },
  {
    "id": 500446,
    "desc": "角色-9-等级47",
    "role_id": 400008,
    "level": 47,
    "need_exp": 100
  },
  {
    "id": 500447,
    "desc": "角色-9-等级48",
    "role_id": 400008,
    "level": 48,
    "need_exp": 100
  },
  {
    "id": 500448,
    "desc": "角色-9-等级49",
    "role_id": 400008,
    "level": 49,
    "need_exp": 100
  },
  {
    "id": 500449,
    "desc": "角色-9-等级50",
    "role_id": 400008,
    "level": 50,
    "need_exp": 100
  },
  {
    "id": 500450,
    "desc": "角色-10-等级1",
    "role_id": 400009,
    "level": 1,
    "need_exp": 100
  },
  {
    "id": 500451,
    "desc": "角色-10-等级2",
    "role_id": 400009,
    "level": 2,
    "need_exp": 100
  },
  {
    "id": 500452,
    "desc": "角色-10-等级3",
    "role_id": 400009,
    "level": 3,
    "need_exp": 100
  },
  {
    "id": 500453,
    "desc": "角色-10-等级4",
    "role_id": 400009,
    "level": 4,
    "need_exp": 100
  },
  {
    "id": 500454,
    "desc": "角色-10-等级5",
    "role_id": 400009,
    "level": 5,
    "need_exp": 100
  },
  {
    "id": 500455,
    "desc": "角色-10-等级6",
    "role_id": 400009,
    "level": 6,
    "need_exp": 100
  },
  {
    "id": 500456,
    "desc": "角色-10-等级7",
    "role_id": 400009,
    "level": 7,
    "need_exp": 100
  },
  {
    "id": 500457,
    "desc": "角色-10-等级8",
    "role_id": 400009,
    "level": 8,
    "need_exp": 100
  },
  {
    "id": 500458,
    "desc": "角色-10-等级9",
    "role_id": 400009,
    "level": 9,
    "need_exp": 100
  },
  {
    "id": 500459,
    "desc": "角色-10-等级10",
    "role_id": 400009,
    "level": 10,
    "need_exp": 100
  },
  {
    "id": 500460,
    "desc": "角色-10-等级11",
    "role_id": 400009,
    "level": 11,
    "need_exp": 100
  },
  {
    "id": 500461,
    "desc": "角色-10-等级12",
    "role_id": 400009,
    "level": 12,
    "need_exp": 100
  },
  {
    "id": 500462,
    "desc": "角色-10-等级13",
    "role_id": 400009,
    "level": 13,
    "need_exp": 100
  },
  {
    "id": 500463,
    "desc": "角色-10-等级14",
    "role_id": 400009,
    "level": 14,
    "need_exp": 100
  },
  {
    "id": 500464,
    "desc": "角色-10-等级15",
    "role_id": 400009,
    "level": 15,
    "need_exp": 100
  },
  {
    "id": 500465,
    "desc": "角色-10-等级16",
    "role_id": 400009,
    "level": 16,
    "need_exp": 100
  },
  {
    "id": 500466,
    "desc": "角色-10-等级17",
    "role_id": 400009,
    "level": 17,
    "need_exp": 100
  },
  {
    "id": 500467,
    "desc": "角色-10-等级18",
    "role_id": 400009,
    "level": 18,
    "need_exp": 100
  },
  {
    "id": 500468,
    "desc": "角色-10-等级19",
    "role_id": 400009,
    "level": 19,
    "need_exp": 100
  },
  {
    "id": 500469,
    "desc": "角色-10-等级20",
    "role_id": 400009,
    "level": 20,
    "need_exp": 100
  },
  {
    "id": 500470,
    "desc": "角色-10-等级21",
    "role_id": 400009,
    "level": 21,
    "need_exp": 100
  },
  {
    "id": 500471,
    "desc": "角色-10-等级22",
    "role_id": 400009,
    "level": 22,
    "need_exp": 100
  },
  {
    "id": 500472,
    "desc": "角色-10-等级23",
    "role_id": 400009,
    "level": 23,
    "need_exp": 100
  },
  {
    "id": 500473,
    "desc": "角色-10-等级24",
    "role_id": 400009,
    "level": 24,
    "need_exp": 100
  },
  {
    "id": 500474,
    "desc": "角色-10-等级25",
    "role_id": 400009,
    "level": 25,
    "need_exp": 100
  },
  {
    "id": 500475,
    "desc": "角色-10-等级26",
    "role_id": 400009,
    "level": 26,
    "need_exp": 100
  },
  {
    "id": 500476,
    "desc": "角色-10-等级27",
    "role_id": 400009,
    "level": 27,
    "need_exp": 100
  },
  {
    "id": 500477,
    "desc": "角色-10-等级28",
    "role_id": 400009,
    "level": 28,
    "need_exp": 100
  },
  {
    "id": 500478,
    "desc": "角色-10-等级29",
    "role_id": 400009,
    "level": 29,
    "need_exp": 100
  },
  {
    "id": 500479,
    "desc": "角色-10-等级30",
    "role_id": 400009,
    "level": 30,
    "need_exp": 100
  },
  {
    "id": 500480,
    "desc": "角色-10-等级31",
    "role_id": 400009,
    "level": 31,
    "need_exp": 100
  },
  {
    "id": 500481,
    "desc": "角色-10-等级32",
    "role_id": 400009,
    "level": 32,
    "need_exp": 100
  },
  {
    "id": 500482,
    "desc": "角色-10-等级33",
    "role_id": 400009,
    "level": 33,
    "need_exp": 100
  },
  {
    "id": 500483,
    "desc": "角色-10-等级34",
    "role_id": 400009,
    "level": 34,
    "need_exp": 100
  },
  {
    "id": 500484,
    "desc": "角色-10-等级35",
    "role_id": 400009,
    "level": 35,
    "need_exp": 100
  },
  {
    "id": 500485,
    "desc": "角色-10-等级36",
    "role_id": 400009,
    "level": 36,
    "need_exp": 100
  },
  {
    "id": 500486,
    "desc": "角色-10-等级37",
    "role_id": 400009,
    "level": 37,
    "need_exp": 100
  },
  {
    "id": 500487,
    "desc": "角色-10-等级38",
    "role_id": 400009,
    "level": 38,
    "need_exp": 100
  },
  {
    "id": 500488,
    "desc": "角色-10-等级39",
    "role_id": 400009,
    "level": 39,
    "need_exp": 100
  },
  {
    "id": 500489,
    "desc": "角色-10-等级40",
    "role_id": 400009,
    "level": 40,
    "need_exp": 100
  },
  {
    "id": 500490,
    "desc": "角色-10-等级41",
    "role_id": 400009,
    "level": 41,
    "need_exp": 100
  },
  {
    "id": 500491,
    "desc": "角色-10-等级42",
    "role_id": 400009,
    "level": 42,
    "need_exp": 100
  },
  {
    "id": 500492,
    "desc": "角色-10-等级43",
    "role_id": 400009,
    "level": 43,
    "need_exp": 100
  },
  {
    "id": 500493,
    "desc": "角色-10-等级44",
    "role_id": 400009,
    "level": 44,
    "need_exp": 100
  },
  {
    "id": 500494,
    "desc": "角色-10-等级45",
    "role_id": 400009,
    "level": 45,
    "need_exp": 100
  },
  {
    "id": 500495,
    "desc": "角色-10-等级46",
    "role_id": 400009,
    "level": 46,
    "need_exp": 100
  },
  {
    "id": 500496,
    "desc": "角色-10-等级47",
    "role_id": 400009,
    "level": 47,
    "need_exp": 100
  },
  {
    "id": 500497,
    "desc": "角色-10-等级48",
    "role_id": 400009,
    "level": 48,
    "need_exp": 100
  },
  {
    "id": 500498,
    "desc": "角色-10-等级49",
    "role_id": 400009,
    "level": 49,
    "need_exp": 100
  },
  {
    "id": 500499,
    "desc": "角色-10-等级50",
    "role_id": 400009,
    "level": 50,
    "need_exp": 100
  },
  {
    "id": 500500,
    "desc": "角色-11-等级1",
    "role_id": 400010,
    "level": 1,
    "need_exp": 100
  },
  {
    "id": 500501,
    "desc": "角色-11-等级2",
    "role_id": 400010,
    "level": 2,
    "need_exp": 100
  },
  {
    "id": 500502,
    "desc": "角色-11-等级3",
    "role_id": 400010,
    "level": 3,
    "need_exp": 100
  },
  {
    "id": 500503,
    "desc": "角色-11-等级4",
    "role_id": 400010,
    "level": 4,
    "need_exp": 100
  },
  {
    "id": 500504,
    "desc": "角色-11-等级5",
    "role_id": 400010,
    "level": 5,
    "need_exp": 100
  },
  {
    "id": 500505,
    "desc": "角色-11-等级6",
    "role_id": 400010,
    "level": 6,
    "need_exp": 100
  },
  {
    "id": 500506,
    "desc": "角色-11-等级7",
    "role_id": 400010,
    "level": 7,
    "need_exp": 100
  },
  {
    "id": 500507,
    "desc": "角色-11-等级8",
    "role_id": 400010,
    "level": 8,
    "need_exp": 100
  },
  {
    "id": 500508,
    "desc": "角色-11-等级9",
    "role_id": 400010,
    "level": 9,
    "need_exp": 100
  },
  {
    "id": 500509,
    "desc": "角色-11-等级10",
    "role_id": 400010,
    "level": 10,
    "need_exp": 100
  },
  {
    "id": 500510,
    "desc": "角色-11-等级11",
    "role_id": 400010,
    "level": 11,
    "need_exp": 100
  },
  {
    "id": 500511,
    "desc": "角色-11-等级12",
    "role_id": 400010,
    "level": 12,
    "need_exp": 100
  },
  {
    "id": 500512,
    "desc": "角色-11-等级13",
    "role_id": 400010,
    "level": 13,
    "need_exp": 100
  },
  {
    "id": 500513,
    "desc": "角色-11-等级14",
    "role_id": 400010,
    "level": 14,
    "need_exp": 100
  },
  {
    "id": 500514,
    "desc": "角色-11-等级15",
    "role_id": 400010,
    "level": 15,
    "need_exp": 100
  },
  {
    "id": 500515,
    "desc": "角色-11-等级16",
    "role_id": 400010,
    "level": 16,
    "need_exp": 100
  },
  {
    "id": 500516,
    "desc": "角色-11-等级17",
    "role_id": 400010,
    "level": 17,
    "need_exp": 100
  },
  {
    "id": 500517,
    "desc": "角色-11-等级18",
    "role_id": 400010,
    "level": 18,
    "need_exp": 100
  },
  {
    "id": 500518,
    "desc": "角色-11-等级19",
    "role_id": 400010,
    "level": 19,
    "need_exp": 100
  },
  {
    "id": 500519,
    "desc": "角色-11-等级20",
    "role_id": 400010,
    "level": 20,
    "need_exp": 100
  },
  {
    "id": 500520,
    "desc": "角色-11-等级21",
    "role_id": 400010,
    "level": 21,
    "need_exp": 100
  },
  {
    "id": 500521,
    "desc": "角色-11-等级22",
    "role_id": 400010,
    "level": 22,
    "need_exp": 100
  },
  {
    "id": 500522,
    "desc": "角色-11-等级23",
    "role_id": 400010,
    "level": 23,
    "need_exp": 100
  },
  {
    "id": 500523,
    "desc": "角色-11-等级24",
    "role_id": 400010,
    "level": 24,
    "need_exp": 100
  },
  {
    "id": 500524,
    "desc": "角色-11-等级25",
    "role_id": 400010,
    "level": 25,
    "need_exp": 100
  },
  {
    "id": 500525,
    "desc": "角色-11-等级26",
    "role_id": 400010,
    "level": 26,
    "need_exp": 100
  },
  {
    "id": 500526,
    "desc": "角色-11-等级27",
    "role_id": 400010,
    "level": 27,
    "need_exp": 100
  },
  {
    "id": 500527,
    "desc": "角色-11-等级28",
    "role_id": 400010,
    "level": 28,
    "need_exp": 100
  },
  {
    "id": 500528,
    "desc": "角色-11-等级29",
    "role_id": 400010,
    "level": 29,
    "need_exp": 100
  },
  {
    "id": 500529,
    "desc": "角色-11-等级30",
    "role_id": 400010,
    "level": 30,
    "need_exp": 100
  },
  {
    "id": 500530,
    "desc": "角色-11-等级31",
    "role_id": 400010,
    "level": 31,
    "need_exp": 100
  },
  {
    "id": 500531,
    "desc": "角色-11-等级32",
    "role_id": 400010,
    "level": 32,
    "need_exp": 100
  },
  {
    "id": 500532,
    "desc": "角色-11-等级33",
    "role_id": 400010,
    "level": 33,
    "need_exp": 100
  },
  {
    "id": 500533,
    "desc": "角色-11-等级34",
    "role_id": 400010,
    "level": 34,
    "need_exp": 100
  },
  {
    "id": 500534,
    "desc": "角色-11-等级35",
    "role_id": 400010,
    "level": 35,
    "need_exp": 100
  },
  {
    "id": 500535,
    "desc": "角色-11-等级36",
    "role_id": 400010,
    "level": 36,
    "need_exp": 100
  },
  {
    "id": 500536,
    "desc": "角色-11-等级37",
    "role_id": 400010,
    "level": 37,
    "need_exp": 100
  },
  {
    "id": 500537,
    "desc": "角色-11-等级38",
    "role_id": 400010,
    "level": 38,
    "need_exp": 100
  },
  {
    "id": 500538,
    "desc": "角色-11-等级39",
    "role_id": 400010,
    "level": 39,
    "need_exp": 100
  },
  {
    "id": 500539,
    "desc": "角色-11-等级40",
    "role_id": 400010,
    "level": 40,
    "need_exp": 100
  },
  {
    "id": 500540,
    "desc": "角色-11-等级41",
    "role_id": 400010,
    "level": 41,
    "need_exp": 100
  },
  {
    "id": 500541,
    "desc": "角色-11-等级42",
    "role_id": 400010,
    "level": 42,
    "need_exp": 100
  },
  {
    "id": 500542,
    "desc": "角色-11-等级43",
    "role_id": 400010,
    "level": 43,
    "need_exp": 100
  },
  {
    "id": 500543,
    "desc": "角色-11-等级44",
    "role_id": 400010,
    "level": 44,
    "need_exp": 100
  },
  {
    "id": 500544,
    "desc": "角色-11-等级45",
    "role_id": 400010,
    "level": 45,
    "need_exp": 100
  },
  {
    "id": 500545,
    "desc": "角色-11-等级46",
    "role_id": 400010,
    "level": 46,
    "need_exp": 100
  },
  {
    "id": 500546,
    "desc": "角色-11-等级47",
    "role_id": 400010,
    "level": 47,
    "need_exp": 100
  },
  {
    "id": 500547,
    "desc": "角色-11-等级48",
    "role_id": 400010,
    "level": 48,
    "need_exp": 100
  },
  {
    "id": 500548,
    "desc": "角色-11-等级49",
    "role_id": 400010,
    "level": 49,
    "need_exp": 100
  },
  {
    "id": 500549,
    "desc": "角色-11-等级50",
    "role_id": 400010,
    "level": 50,
    "need_exp": 100
  }
]